pyro_compiler/__init__.py
pyro_compiler/cli/__init__.py
pyro_compiler/cli/args.py
pyro_compiler/cli/cli.py
pyro_compiler/cli/commands.py
pyro_compiler/cli/utils.py
pyro_compiler/compiler/__init__.py
pyro_compiler/compiler/compiler.py
pyro_compiler/compiler/errors/__init__.py
pyro_compiler/compiler/errors/compile_time_message.py
pyro_compiler/compiler/errors/error_type.py
pyro_compiler/compiler/errors/message_factory.py
pyro_compiler/compiler/errors/message_registry.py
pyro_compiler/compiler/errors/utils.py
pyro_compiler/compiler/generation/__init__.py
pyro_compiler/compiler/generation/generation.py
pyro_compiler/compiler/generation/utils.py
pyro_compiler/compiler/parsing/__init__.py
pyro_compiler/compiler/parsing/parsing.py
pyro_compiler/compiler/parsing/utils.py
pyro_compiler/compiler/representation/__init__.py
pyro_compiler/compiler/representation/command.py
pyro_compiler/compiler/representation/ir_builder.py
pyro_compiler/compiler/representation/label.py
pyro_compiler/compiler/representation/pseudo_register.py
pyro_compiler/compiler/representation/representation.py
pyro_compiler/compiler/representation/utils.py
pyro_compiler/compiler/representation/variable.py
pyro_compiler/compiler/tokens.py
pyro_compiler/state/__init__.py
pyro_compiler/state/compiler_commands.py
pyro_compiler/state/compiler_state.py
pyro_compiler-0.1.0.dist-info/METADATA
pyro_compiler-0.1.0.dist-info/WHEEL
pyro_compiler-0.1.0.dist-info/RECORD
