Metadata-Version: 2.1
Name: pyro_compiler
Version: 0.1.0
Summary: 
Author: Antony Redman
Author-email: RumataYounger@gmail.com
Requires-Python: >=3.11,<4.0
Classifier: Programming Language :: Python :: 3
Classifier: Programming Language :: Python :: 3.11
